<annotation>
	<folder>JPEGImages</folder>
	<filename>1854.jpg</filename>
	<path>D:\deeplearning_github\keras-yolo3-master\VOCdevkit\VOC2007\JPEGImages\1854.jpg</path>
	<source>
		<database>Unknown</database>
	</source>
	<size>
		<width>640</width>
		<height>480</height>
		<depth>3</depth>
	</size>
	<segmented>0</segmented>
	<object>
		<name>normal_banana</name>
		<pose>Unspecified</pose>
		<truncated>0</truncated>
		<difficult>0</difficult>
		<bndbox>
			<xmin>136</xmin>
			<ymin>93</ymin>
			<xmax>290</xmax>
			<ymax>403</ymax>
		</bndbox>
	</object>
	<object>
		<name>fresh_banana</name>
		<pose>Unspecified</pose>
		<truncated>0</truncated>
		<difficult>0</difficult>
		<bndbox>
			<xmin>261</xmin>
			<ymin>134</ymin>
			<xmax>518</xmax>
			<ymax>429</ymax>
		</bndbox>
	</object>
</annotation>
