<annotation>
	<folder>JPEGImages</folder>
	<filename>595.jpg</filename>
	<path>D:\deeplearning_github\keras-yolo3-master\VOCdevkit\VOC2007\JPEGImages\595.jpg</path>
	<source>
		<database>Unknown</database>
	</source>
	<size>
		<width>630</width>
		<height>430</height>
		<depth>3</depth>
	</size>
	<segmented>0</segmented>
	<object>
		<name>fresh_banana</name>
		<pose>Unspecified</pose>
		<truncated>1</truncated>
		<difficult>0</difficult>
		<bndbox>
			<xmin>42</xmin>
			<ymin>11</ymin>
			<xmax>592</xmax>
			<ymax>430</ymax>
		</bndbox>
	</object>
</annotation>
